lazy_mongo_log/__init__.py
lazy_mongo_log/lazy_mongo_log.py
lazy_mongo_log/schemas.py
lazy_mongo_log-0.1.7.dist-info/METADATA
lazy_mongo_log-0.1.7.dist-info/WHEEL
lazy_mongo_log-0.1.7.dist-info/RECORD
